[
  {
    "분류": "요툰하임",
    "보스": "파르바 (오후)",
    "출현 시간": "23:13"
  },
  {
    "분류": "요툰하임",
    "보스": "셀로비아 (오후)",
    "출현 시간": "23:44"
  },
  {
    "분류": "요툰하임",
    "보스": "니드호그 (오전)",
    "출현 시간": "02:06"
  },
  {
    "분류": "요툰하임",
    "보스": "페티 (오전)",
    "출현 시간": "02:51"
  },
  {
    "분류": "요툰하임",
    "보스": "파르바 (오전)",
    "출현 시간": "11:13"
  },
  {
    "분류": "요툰하임",
    "보스": "셀로비아 (오전)",
    "출현 시간": "11:44"
  },
  {
    "분류": "요툰하임",
    "보스": "니드호그 (오후)",
    "출현 시간": "14:06"
  },
  {
    "분류": "요툰하임",
    "보스": "페티 (오후)",
    "출현 시간": "14:51"
  },
  {
    "분류": "고정일정",
    "보스": "길드경매",
    "출현 시간": "23:00"
  },
  {
    "분류": "절대자",
    "보스": "티르",
    "출현 시간": "06:08"
  },
  {
    "분류": "고정일정",
    "보스": "월드던전",
    "출현 시간": "21:30"
  },
  {
    "분류": "고정일정",
    "보스": "길드쟁탈전",
    "출현 시간": "21:30"
  },
  {
    "분류": "고정일정",
    "보스": "성채",
    "출현 시간": "21:30"
  },
  {
    "분류": "고정일정",
    "보스": "성채",
    "출현 시간": "21:30"
  },
  {
    "분류": "고정일정",
    "보스": "지옥성채",
    "출현 시간": "22:30"
  }
]